maxsee.py
maxsee_viewer.py
maxsee_viewer-1.0.0.dist-info/licenses/LICENSE
maxsee_viewer-1.0.0.dist-info/METADATA
maxsee_viewer-1.0.0.dist-info/WHEEL
maxsee_viewer-1.0.0.dist-info/entry_points.txt
maxsee_viewer-1.0.0.dist-info/top_level.txt
maxsee_viewer-1.0.0.dist-info/RECORD
