Metadata-Version: 2.4
Name: maxsee_viewer
Version: 1.0.0
Summary: Viewer for MaxSee USB/Wifi microscope
Author-email: Johannes Löhnert <loehnert.kde@gmx.de>
Project-URL: Homepage, https://github.com/loehnertj/maxsee_viewer
Classifier: Development Status :: 3 - Alpha
Classifier: Topic :: Scientific/Engineering
Classifier: Programming Language :: Python
Classifier: License :: OSI Approved :: MIT License
Requires-Python: >=3.9
License-File: LICENSE
Requires-Dist: ascii-designer
Requires-Dist: pillow
Dynamic: license-file
